{
    "openapi": "3.0.4",
    "info": {
        "title": "Familien-Kochbuch API",
        "description": "Private Rezept-Sammlung — Phase 1 API.",
        "version": "v1"
    },
    "paths": {
        "/api/auth/signup": {
            "post": {
                "tags": [
                    "Auth"
                ],
                "parameters": [
                    {
                        "name": "token",
                        "in": "query",
                        "schema": {
                            "type": "string"
                        }
                    }
                ],
                "requestBody": {
                    "content": {
                        "application/json": {
                            "schema": {
                                "$ref": "#/components/schemas/SignupRequest"
                            }
                        }
                    },
                    "required": true
                },
                "responses": {
                    "200": {
                        "description": "OK"
                    }
                }
            }
        },
        "/api/auth/login": {
            "post": {
                "tags": [
                    "Auth"
                ],
                "requestBody": {
                    "content": {
                        "application/json": {
                            "schema": {
                                "$ref": "#/components/schemas/LoginRequest"
                            }
                        }
                    },
                    "required": true
                },
                "responses": {
                    "200": {
                        "description": "OK"
                    }
                }
            }
        },
        "/api/auth/refresh": {
            "post": {
                "tags": [
                    "Auth"
                ],
                "responses": {
                    "200": {
                        "description": "OK"
                    }
                }
            }
        },
        "/api/auth/logout": {
            "post": {
                "tags": [
                    "Auth"
                ],
                "responses": {
                    "200": {
                        "description": "OK"
                    }
                }
            }
        },
        "/api/auth/password-reset-request": {
            "post": {
                "tags": [
                    "Auth"
                ],
                "requestBody": {
                    "content": {
                        "application/json": {
                            "schema": {
                                "$ref": "#/components/schemas/PasswordResetRequestBody"
                            }
                        }
                    },
                    "required": true
                },
                "responses": {
                    "200": {
                        "description": "OK"
                    }
                }
            }
        },
        "/api/auth/password-reset": {
            "post": {
                "tags": [
                    "Auth"
                ],
                "requestBody": {
                    "content": {
                        "application/json": {
                            "schema": {
                                "$ref": "#/components/schemas/PasswordResetBody"
                            }
                        }
                    },
                    "required": true
                },
                "responses": {
                    "200": {
                        "description": "OK"
                    }
                }
            }
        },
        "/api/groups": {
            "post": {
                "tags": [
                    "Groups"
                ],
                "requestBody": {
                    "content": {
                        "application/json": {
                            "schema": {
                                "$ref": "#/components/schemas/CreateGroupRequest"
                            }
                        }
                    },
                    "required": true
                },
                "responses": {
                    "200": {
                        "description": "OK"
                    }
                }
            },
            "get": {
                "tags": [
                    "Groups"
                ],
                "responses": {
                    "200": {
                        "description": "OK"
                    }
                }
            }
        },
        "/api/groups/invites": {
            "get": {
                "tags": [
                    "Groups"
                ],
                "responses": {
                    "200": {
                        "description": "OK"
                    }
                }
            }
        },
        "/api/groups/invites/{id}/accept": {
            "post": {
                "tags": [
                    "Groups"
                ],
                "parameters": [
                    {
                        "name": "id",
                        "in": "path",
                        "required": true,
                        "schema": {
                            "type": "string",
                            "format": "uuid"
                        }
                    }
                ],
                "responses": {
                    "200": {
                        "description": "OK"
                    }
                }
            }
        },
        "/api/groups/invites/{id}/decline": {
            "post": {
                "tags": [
                    "Groups"
                ],
                "parameters": [
                    {
                        "name": "id",
                        "in": "path",
                        "required": true,
                        "schema": {
                            "type": "string",
                            "format": "uuid"
                        }
                    }
                ],
                "responses": {
                    "200": {
                        "description": "OK"
                    }
                }
            }
        },
        "/api/groups/{id}": {
            "get": {
                "tags": [
                    "Groups"
                ],
                "parameters": [
                    {
                        "name": "id",
                        "in": "path",
                        "required": true,
                        "schema": {
                            "type": "string",
                            "format": "uuid"
                        }
                    }
                ],
                "responses": {
                    "200": {
                        "description": "OK"
                    }
                }
            },
            "put": {
                "tags": [
                    "Groups"
                ],
                "parameters": [
                    {
                        "name": "id",
                        "in": "path",
                        "required": true,
                        "schema": {
                            "type": "string",
                            "format": "uuid"
                        }
                    }
                ],
                "requestBody": {
                    "content": {
                        "application/json": {
                            "schema": {
                                "$ref": "#/components/schemas/UpdateGroupRequest"
                            }
                        }
                    },
                    "required": true
                },
                "responses": {
                    "200": {
                        "description": "OK"
                    }
                }
            },
            "delete": {
                "tags": [
                    "Groups"
                ],
                "parameters": [
                    {
                        "name": "id",
                        "in": "path",
                        "required": true,
                        "schema": {
                            "type": "string",
                            "format": "uuid"
                        }
                    }
                ],
                "responses": {
                    "200": {
                        "description": "OK"
                    }
                }
            }
        },
        "/api/groups/{id}/invites": {
            "post": {
                "tags": [
                    "Groups"
                ],
                "parameters": [
                    {
                        "name": "id",
                        "in": "path",
                        "required": true,
                        "schema": {
                            "type": "string",
                            "format": "uuid"
                        }
                    }
                ],
                "requestBody": {
                    "content": {
                        "application/json": {
                            "schema": {
                                "$ref": "#/components/schemas/InviteToGroupRequest"
                            }
                        }
                    },
                    "required": true
                },
                "responses": {
                    "200": {
                        "description": "OK"
                    }
                }
            }
        },
        "/api/groups/{id}/members": {
            "get": {
                "tags": [
                    "Groups"
                ],
                "parameters": [
                    {
                        "name": "id",
                        "in": "path",
                        "required": true,
                        "schema": {
                            "type": "string",
                            "format": "uuid"
                        }
                    }
                ],
                "responses": {
                    "200": {
                        "description": "OK"
                    }
                }
            }
        },
        "/api/groups/{id}/members/{userId}": {
            "put": {
                "tags": [
                    "Groups"
                ],
                "parameters": [
                    {
                        "name": "id",
                        "in": "path",
                        "required": true,
                        "schema": {
                            "type": "string",
                            "format": "uuid"
                        }
                    },
                    {
                        "name": "userId",
                        "in": "path",
                        "required": true,
                        "schema": {
                            "type": "string",
                            "format": "uuid"
                        }
                    }
                ],
                "requestBody": {
                    "content": {
                        "application/json": {
                            "schema": {
                                "$ref": "#/components/schemas/ChangeMemberRoleRequest"
                            }
                        }
                    },
                    "required": true
                },
                "responses": {
                    "200": {
                        "description": "OK"
                    }
                }
            },
            "delete": {
                "tags": [
                    "Groups"
                ],
                "parameters": [
                    {
                        "name": "id",
                        "in": "path",
                        "required": true,
                        "schema": {
                            "type": "string",
                            "format": "uuid"
                        }
                    },
                    {
                        "name": "userId",
                        "in": "path",
                        "required": true,
                        "schema": {
                            "type": "string",
                            "format": "uuid"
                        }
                    }
                ],
                "responses": {
                    "200": {
                        "description": "OK"
                    }
                }
            }
        },
        "/api/health": {
            "get": {
                "tags": [
                    "Health"
                ],
                "responses": {
                    "200": {
                        "description": "OK"
                    }
                }
            }
        },
        "/api/invites/app": {
            "post": {
                "tags": [
                    "Invites"
                ],
                "requestBody": {
                    "content": {
                        "application/json": {
                            "schema": {
                                "$ref": "#/components/schemas/CreateInviteRequest"
                            }
                        }
                    },
                    "required": true
                },
                "responses": {
                    "200": {
                        "description": "OK"
                    }
                }
            }
        },
        "/api/invites/app/{token}": {
            "get": {
                "tags": [
                    "Invites"
                ],
                "parameters": [
                    {
                        "name": "token",
                        "in": "path",
                        "required": true,
                        "schema": {
                            "type": "string"
                        }
                    }
                ],
                "responses": {
                    "200": {
                        "description": "OK"
                    }
                }
            }
        },
        "/api/invites/app/{id}": {
            "delete": {
                "tags": [
                    "Invites"
                ],
                "parameters": [
                    {
                        "name": "id",
                        "in": "path",
                        "required": true,
                        "schema": {
                            "type": "string",
                            "format": "uuid"
                        }
                    }
                ],
                "responses": {
                    "200": {
                        "description": "OK"
                    }
                }
            }
        },
        "/api/photos/{path}": {
            "get": {
                "tags": [
                    "Photos"
                ],
                "parameters": [
                    {
                        "name": "path",
                        "in": "path",
                        "required": true,
                        "schema": {
                            "type": "string"
                        }
                    }
                ],
                "responses": {
                    "200": {
                        "description": "OK"
                    }
                }
            }
        },
        "/api/recipes/{id}/ratings": {
            "post": {
                "tags": [
                    "Ratings"
                ],
                "parameters": [
                    {
                        "name": "id",
                        "in": "path",
                        "required": true,
                        "schema": {
                            "type": "string",
                            "format": "uuid"
                        }
                    }
                ],
                "requestBody": {
                    "content": {
                        "application/json": {
                            "schema": {
                                "$ref": "#/components/schemas/UpsertRatingRequest"
                            }
                        }
                    },
                    "required": true
                },
                "responses": {
                    "200": {
                        "description": "OK"
                    }
                }
            },
            "delete": {
                "tags": [
                    "Ratings"
                ],
                "parameters": [
                    {
                        "name": "id",
                        "in": "path",
                        "required": true,
                        "schema": {
                            "type": "string",
                            "format": "uuid"
                        }
                    }
                ],
                "responses": {
                    "200": {
                        "description": "OK"
                    }
                }
            },
            "get": {
                "tags": [
                    "Ratings"
                ],
                "parameters": [
                    {
                        "name": "id",
                        "in": "path",
                        "required": true,
                        "schema": {
                            "type": "string",
                            "format": "uuid"
                        }
                    }
                ],
                "responses": {
                    "200": {
                        "description": "OK"
                    }
                }
            }
        },
        "/api/recipes/{id}/revisions": {
            "get": {
                "tags": [
                    "RecipeRevisions"
                ],
                "parameters": [
                    {
                        "name": "id",
                        "in": "path",
                        "required": true,
                        "schema": {
                            "type": "string",
                            "format": "uuid"
                        }
                    }
                ],
                "responses": {
                    "200": {
                        "description": "OK"
                    }
                }
            }
        },
        "/api/recipes/{id}/revisions/{revisionId}": {
            "get": {
                "tags": [
                    "RecipeRevisions"
                ],
                "parameters": [
                    {
                        "name": "id",
                        "in": "path",
                        "required": true,
                        "schema": {
                            "type": "string",
                            "format": "uuid"
                        }
                    },
                    {
                        "name": "revisionId",
                        "in": "path",
                        "required": true,
                        "schema": {
                            "type": "string",
                            "format": "uuid"
                        }
                    }
                ],
                "responses": {
                    "200": {
                        "description": "OK"
                    }
                }
            }
        },
        "/api/groups/{groupId}/recipes": {
            "post": {
                "tags": [
                    "Recipes"
                ],
                "parameters": [
                    {
                        "name": "groupId",
                        "in": "path",
                        "required": true,
                        "schema": {
                            "type": "string",
                            "format": "uuid"
                        }
                    }
                ],
                "requestBody": {
                    "content": {
                        "application/json": {
                            "schema": {
                                "$ref": "#/components/schemas/CreateRecipeRequest"
                            }
                        }
                    },
                    "required": true
                },
                "responses": {
                    "200": {
                        "description": "OK"
                    }
                }
            },
            "get": {
                "tags": [
                    "Recipes"
                ],
                "parameters": [
                    {
                        "name": "groupId",
                        "in": "path",
                        "required": true,
                        "schema": {
                            "type": "string",
                            "format": "uuid"
                        }
                    },
                    {
                        "name": "page",
                        "in": "query",
                        "schema": {
                            "type": "integer",
                            "format": "int32"
                        }
                    },
                    {
                        "name": "pageSize",
                        "in": "query",
                        "schema": {
                            "type": "integer",
                            "format": "int32"
                        }
                    }
                ],
                "responses": {
                    "200": {
                        "description": "OK"
                    }
                }
            }
        },
        "/api/recipes/{id}": {
            "get": {
                "tags": [
                    "Recipes"
                ],
                "parameters": [
                    {
                        "name": "id",
                        "in": "path",
                        "required": true,
                        "schema": {
                            "type": "string",
                            "format": "uuid"
                        }
                    }
                ],
                "responses": {
                    "200": {
                        "description": "OK"
                    }
                }
            },
            "put": {
                "tags": [
                    "Recipes"
                ],
                "parameters": [
                    {
                        "name": "id",
                        "in": "path",
                        "required": true,
                        "schema": {
                            "type": "string",
                            "format": "uuid"
                        }
                    }
                ],
                "requestBody": {
                    "content": {
                        "application/json": {
                            "schema": {
                                "$ref": "#/components/schemas/UpdateRecipeRequest"
                            }
                        }
                    },
                    "required": true
                },
                "responses": {
                    "200": {
                        "description": "OK"
                    }
                }
            },
            "delete": {
                "tags": [
                    "Recipes"
                ],
                "parameters": [
                    {
                        "name": "id",
                        "in": "path",
                        "required": true,
                        "schema": {
                            "type": "string",
                            "format": "uuid"
                        }
                    }
                ],
                "responses": {
                    "200": {
                        "description": "OK"
                    }
                }
            }
        },
        "/api/recipes/{id}/photos": {
            "delete": {
                "tags": [
                    "Recipes"
                ],
                "parameters": [
                    {
                        "name": "id",
                        "in": "path",
                        "required": true,
                        "schema": {
                            "type": "string",
                            "format": "uuid"
                        }
                    }
                ],
                "requestBody": {
                    "content": {
                        "application/json": {
                            "schema": {
                                "$ref": "#/components/schemas/RemovePhotoRequest"
                            }
                        }
                    },
                    "required": true
                },
                "responses": {
                    "200": {
                        "description": "OK"
                    }
                }
            }
        },
        "/api/recipes/{id}/fork": {
            "post": {
                "tags": [
                    "Recipes"
                ],
                "parameters": [
                    {
                        "name": "id",
                        "in": "path",
                        "required": true,
                        "schema": {
                            "type": "string",
                            "format": "uuid"
                        }
                    }
                ],
                "requestBody": {
                    "content": {
                        "application/json": {
                            "schema": {
                                "$ref": "#/components/schemas/ForkRecipeRequest"
                            }
                        }
                    },
                    "required": true
                },
                "responses": {
                    "200": {
                        "description": "OK"
                    }
                }
            }
        },
        "/api/groups/{groupId}/recipes/search": {
            "get": {
                "tags": [
                    "Search"
                ],
                "parameters": [
                    {
                        "name": "groupId",
                        "in": "path",
                        "required": true,
                        "schema": {
                            "type": "string",
                            "format": "uuid"
                        }
                    },
                    {
                        "name": "q",
                        "in": "query",
                        "schema": {
                            "type": "string"
                        }
                    },
                    {
                        "name": "tags",
                        "in": "query",
                        "schema": {
                            "type": "string"
                        }
                    },
                    {
                        "name": "minRating",
                        "in": "query",
                        "schema": {
                            "type": "number",
                            "format": "double"
                        }
                    },
                    {
                        "name": "maxPrepTime",
                        "in": "query",
                        "schema": {
                            "type": "integer",
                            "format": "int32"
                        }
                    },
                    {
                        "name": "createdBy",
                        "in": "query",
                        "schema": {
                            "type": "string",
                            "format": "uuid"
                        }
                    },
                    {
                        "name": "sort",
                        "in": "query",
                        "schema": {
                            "type": "string"
                        }
                    },
                    {
                        "name": "page",
                        "in": "query",
                        "schema": {
                            "type": "integer",
                            "format": "int32"
                        }
                    },
                    {
                        "name": "pageSize",
                        "in": "query",
                        "schema": {
                            "type": "integer",
                            "format": "int32"
                        }
                    }
                ],
                "responses": {
                    "200": {
                        "description": "OK"
                    }
                }
            }
        },
        "/api/groups/{groupId}/recipes/random": {
            "get": {
                "tags": [
                    "Search"
                ],
                "parameters": [
                    {
                        "name": "groupId",
                        "in": "path",
                        "required": true,
                        "schema": {
                            "type": "string",
                            "format": "uuid"
                        }
                    },
                    {
                        "name": "q",
                        "in": "query",
                        "schema": {
                            "type": "string"
                        }
                    },
                    {
                        "name": "tags",
                        "in": "query",
                        "schema": {
                            "type": "string"
                        }
                    },
                    {
                        "name": "minRating",
                        "in": "query",
                        "schema": {
                            "type": "number",
                            "format": "double"
                        }
                    },
                    {
                        "name": "maxPrepTime",
                        "in": "query",
                        "schema": {
                            "type": "integer",
                            "format": "int32"
                        }
                    },
                    {
                        "name": "createdBy",
                        "in": "query",
                        "schema": {
                            "type": "string",
                            "format": "uuid"
                        }
                    },
                    {
                        "name": "sort",
                        "in": "query",
                        "schema": {
                            "type": "string"
                        }
                    }
                ],
                "responses": {
                    "200": {
                        "description": "OK"
                    }
                }
            }
        },
        "/api/groups/{groupId}/tags": {
            "get": {
                "tags": [
                    "Tags"
                ],
                "parameters": [
                    {
                        "name": "groupId",
                        "in": "path",
                        "required": true,
                        "schema": {
                            "type": "string",
                            "format": "uuid"
                        }
                    }
                ],
                "responses": {
                    "200": {
                        "description": "OK"
                    }
                }
            },
            "post": {
                "tags": [
                    "Tags"
                ],
                "parameters": [
                    {
                        "name": "groupId",
                        "in": "path",
                        "required": true,
                        "schema": {
                            "type": "string",
                            "format": "uuid"
                        }
                    }
                ],
                "requestBody": {
                    "content": {
                        "application/json": {
                            "schema": {
                                "$ref": "#/components/schemas/CreateTagRequest"
                            }
                        }
                    },
                    "required": true
                },
                "responses": {
                    "200": {
                        "description": "OK"
                    }
                }
            }
        },
        "/api/groups/{groupId}/tags/{tagId}": {
            "delete": {
                "tags": [
                    "Tags"
                ],
                "parameters": [
                    {
                        "name": "groupId",
                        "in": "path",
                        "required": true,
                        "schema": {
                            "type": "string",
                            "format": "uuid"
                        }
                    },
                    {
                        "name": "tagId",
                        "in": "path",
                        "required": true,
                        "schema": {
                            "type": "string",
                            "format": "uuid"
                        }
                    }
                ],
                "responses": {
                    "200": {
                        "description": "OK"
                    }
                }
            }
        },
        "/api/users/search": {
            "get": {
                "tags": [
                    "Users"
                ],
                "parameters": [
                    {
                        "name": "q",
                        "in": "query",
                        "schema": {
                            "type": "string"
                        }
                    },
                    {
                        "name": "excludeGroupId",
                        "in": "query",
                        "schema": {
                            "type": "string",
                            "format": "uuid"
                        }
                    },
                    {
                        "name": "limit",
                        "in": "query",
                        "schema": {
                            "type": "integer",
                            "format": "int32"
                        }
                    }
                ],
                "responses": {
                    "200": {
                        "description": "OK"
                    }
                }
            }
        }
    },
    "components": {
        "schemas": {
            "ChangeMemberRoleRequest": {
                "type": "object",
                "properties": {
                    "role": {
                        "type": "string",
                        "nullable": true
                    }
                },
                "additionalProperties": false
            },
            "CreateGroupRequest": {
                "type": "object",
                "properties": {
                    "name": {
                        "type": "string",
                        "nullable": true
                    },
                    "description": {
                        "type": "string",
                        "nullable": true
                    },
                    "defaultServings": {
                        "type": "number",
                        "format": "double",
                        "nullable": true
                    }
                },
                "additionalProperties": false
            },
            "CreateInviteRequest": {
                "type": "object",
                "properties": {
                    "email": {
                        "type": "string",
                        "nullable": true
                    }
                },
                "additionalProperties": false
            },
            "CreateRecipeRequest": {
                "type": "object",
                "properties": {
                    "title": {
                        "type": "string",
                        "nullable": true
                    },
                    "description": {
                        "type": "string",
                        "nullable": true
                    },
                    "defaultServings": {
                        "type": "integer",
                        "format": "int32"
                    },
                    "prepTimeMinutes": {
                        "type": "integer",
                        "format": "int32",
                        "nullable": true
                    },
                    "difficulty": {
                        "type": "integer",
                        "format": "int32"
                    },
                    "sourceUrl": {
                        "type": "string",
                        "nullable": true
                    },
                    "ingredients": {
                        "type": "array",
                        "items": {
                            "$ref": "#/components/schemas/IngredientRequest"
                        },
                        "nullable": true
                    },
                    "steps": {
                        "type": "array",
                        "items": {
                            "$ref": "#/components/schemas/StepRequest"
                        },
                        "nullable": true
                    },
                    "tagIds": {
                        "type": "array",
                        "items": {
                            "type": "string",
                            "format": "uuid"
                        },
                        "nullable": true
                    }
                },
                "additionalProperties": false
            },
            "CreateTagRequest": {
                "type": "object",
                "properties": {
                    "name": {
                        "type": "string",
                        "nullable": true
                    },
                    "category": {
                        "type": "string",
                        "nullable": true
                    }
                },
                "additionalProperties": false
            },
            "ForkRecipeRequest": {
                "type": "object",
                "properties": {
                    "targetGroupId": {
                        "type": "string",
                        "format": "uuid"
                    }
                },
                "additionalProperties": false
            },
            "IngredientRequest": {
                "type": "object",
                "properties": {
                    "position": {
                        "type": "integer",
                        "format": "int32"
                    },
                    "quantity": {
                        "type": "number",
                        "format": "double",
                        "nullable": true
                    },
                    "unit": {
                        "type": "string",
                        "nullable": true
                    },
                    "name": {
                        "type": "string",
                        "nullable": true
                    },
                    "note": {
                        "type": "string",
                        "nullable": true
                    },
                    "scalable": {
                        "type": "boolean"
                    }
                },
                "additionalProperties": false
            },
            "InviteToGroupRequest": {
                "type": "object",
                "properties": {
                    "invitedUserId": {
                        "type": "string",
                        "format": "uuid"
                    }
                },
                "additionalProperties": false
            },
            "LoginRequest": {
                "type": "object",
                "properties": {
                    "email": {
                        "type": "string",
                        "nullable": true
                    },
                    "password": {
                        "type": "string",
                        "nullable": true
                    }
                },
                "additionalProperties": false
            },
            "PasswordResetBody": {
                "type": "object",
                "properties": {
                    "token": {
                        "type": "string",
                        "nullable": true
                    },
                    "newPassword": {
                        "type": "string",
                        "nullable": true
                    }
                },
                "additionalProperties": false
            },
            "PasswordResetRequestBody": {
                "type": "object",
                "properties": {
                    "email": {
                        "type": "string",
                        "nullable": true
                    }
                },
                "additionalProperties": false
            },
            "RemovePhotoRequest": {
                "type": "object",
                "properties": {
                    "url": {
                        "type": "string",
                        "nullable": true
                    }
                },
                "additionalProperties": false
            },
            "SignupRequest": {
                "type": "object",
                "properties": {
                    "email": {
                        "type": "string",
                        "nullable": true
                    },
                    "password": {
                        "type": "string",
                        "nullable": true
                    },
                    "displayName": {
                        "type": "string",
                        "nullable": true
                    }
                },
                "additionalProperties": false
            },
            "StepRequest": {
                "type": "object",
                "properties": {
                    "position": {
                        "type": "integer",
                        "format": "int32"
                    },
                    "content": {
                        "type": "string",
                        "nullable": true
                    }
                },
                "additionalProperties": false
            },
            "UpdateGroupRequest": {
                "type": "object",
                "properties": {
                    "name": {
                        "type": "string",
                        "nullable": true
                    },
                    "description": {
                        "type": "string",
                        "nullable": true
                    },
                    "defaultServings": {
                        "type": "number",
                        "format": "double",
                        "nullable": true
                    },
                    "coverImageUrl": {
                        "type": "string",
                        "nullable": true
                    }
                },
                "additionalProperties": false
            },
            "UpdateRecipeRequest": {
                "type": "object",
                "properties": {
                    "title": {
                        "type": "string",
                        "nullable": true
                    },
                    "description": {
                        "type": "string",
                        "nullable": true
                    },
                    "defaultServings": {
                        "type": "integer",
                        "format": "int32"
                    },
                    "prepTimeMinutes": {
                        "type": "integer",
                        "format": "int32",
                        "nullable": true
                    },
                    "difficulty": {
                        "type": "integer",
                        "format": "int32"
                    },
                    "sourceUrl": {
                        "type": "string",
                        "nullable": true
                    },
                    "ingredients": {
                        "type": "array",
                        "items": {
                            "$ref": "#/components/schemas/IngredientRequest"
                        },
                        "nullable": true
                    },
                    "steps": {
                        "type": "array",
                        "items": {
                            "$ref": "#/components/schemas/StepRequest"
                        },
                        "nullable": true
                    },
                    "tagIds": {
                        "type": "array",
                        "items": {
                            "type": "string",
                            "format": "uuid"
                        },
                        "nullable": true
                    }
                },
                "additionalProperties": false
            },
            "UpsertRatingRequest": {
                "type": "object",
                "properties": {
                    "stars": {
                        "type": "integer",
                        "format": "int32"
                    },
                    "comment": {
                        "type": "string",
                        "nullable": true
                    }
                },
                "additionalProperties": false
            }
        },
        "securitySchemes": {
            "Bearer": {
                "type": "http",
                "description": "JWT Bearer token from POST /api/auth/login",
                "scheme": "bearer",
                "bearerFormat": "JWT"
            }
        }
    },
    "security": [
        {
            "Bearer": []
        }
    ]
}
